README.md
setup.py
calendarific/__init__.py
python_calendarific.egg-info/PKG-INFO
python_calendarific.egg-info/SOURCES.txt
python_calendarific.egg-info/dependency_links.txt
python_calendarific.egg-info/top_level.txt