Metadata-Version: 1.0
Name: python-calendarific
Version: 1.0.0
Summary: Official Python library for the Calendarific Global Holiday API - https://calendarific.com
Home-page: https://calendarific.com
Author: Calendarific Tech Team
Author-email: info@calendarific.com
License: MIT
Keywords: python,calendarific,holiday,api,calendar,calendarific,public holidays,observances,school holidays,bank holidays,events,countries
Platform: UNKNOWN
